odoo/addons/l10n_de_cooperator/README.rst
odoo/addons/l10n_de_cooperator/__init__.py
odoo/addons/l10n_de_cooperator/__manifest__.py
odoo/addons/l10n_de_cooperator/i18n/it.po
odoo/addons/l10n_de_cooperator/i18n/l10n_de_cooperator.pot
odoo/addons/l10n_de_cooperator/models/__init__.py
odoo/addons/l10n_de_cooperator/models/res_partner.py
odoo/addons/l10n_de_cooperator/models/subscription_request.py
odoo/addons/l10n_de_cooperator/readme/CONTRIBUTORS.rst
odoo/addons/l10n_de_cooperator/readme/DESCRIPTION.rst
odoo/addons/l10n_de_cooperator/static/description/icon.png
odoo/addons/l10n_de_cooperator/static/description/index.html
odoo/addons/l10n_de_cooperator/views/subscription_template.xml
odoo_addon_l10n_de_cooperator-16.0.1.0.0.5.dist-info/METADATA
odoo_addon_l10n_de_cooperator-16.0.1.0.0.5.dist-info/WHEEL
odoo_addon_l10n_de_cooperator-16.0.1.0.0.5.dist-info/top_level.txt
odoo_addon_l10n_de_cooperator-16.0.1.0.0.5.dist-info/RECORD
